strands_google/__init__.py
strands_google/gmail_helpers.py
strands_google/google_auth.py
strands_google/use_google.py
strands_google-0.1.0.dist-info/METADATA
strands_google-0.1.0.dist-info/WHEEL
strands_google-0.1.0.dist-info/licenses/LICENSE
strands_google-0.1.0.dist-info/RECORD
