Metadata-Version: 2.4
Name: strands-google
Version: 0.1.0
Summary: Google API integration tools for Strands Agents
Project-URL: Homepage, https://github.com/cagataycali/strands-google
Project-URL: Documentation, https://github.com/cagataycali/strands-google#readme
Project-URL: Repository, https://github.com/cagataycali/strands-google
Project-URL: Issues, https://github.com/cagataycali/strands-google/issues
Author-email: Strands Community <hello@strands.ai>
License: MIT
License-File: LICENSE
Keywords: agents,ai,api,gmail,google,oauth,strands
Classifier: Development Status :: 3 - Alpha
Classifier: Intended Audience :: Developers
Classifier: License :: OSI Approved :: MIT License
Classifier: Programming Language :: Python :: 3
Classifier: Programming Language :: Python :: 3.8
Classifier: Programming Language :: Python :: 3.9
Classifier: Programming Language :: Python :: 3.10
Classifier: Programming Language :: Python :: 3.11
Classifier: Programming Language :: Python :: 3.12
Requires-Python: >=3.8
Requires-Dist: google-api-python-client
Requires-Dist: google-auth-httplib2
Requires-Dist: google-auth-oauthlib
Requires-Dist: strands-agents
